caospy/__init__.py
caospy/core.py
caospy/poincare.py
caospy/predet_systems.py
caospy/trajectories.py
caospy-0.0.1.dist-info/LICENSE
caospy-0.0.1.dist-info/METADATA
caospy-0.0.1.dist-info/WHEEL
caospy-0.0.1.dist-info/top_level.txt
caospy-0.0.1.dist-info/RECORD
