Metadata-Version: 2.1
Name: caospy
Version: 0.0.1
Summary: Dynamic systems analysis
Home-page: https://github.com/Colman-Bertolo/Caospy
Author: Juan Colman, Sebastián Bertolo
Author-email: juancolmanot@gmail.com
License: The MIT License
Keywords: caospy,dynamic system,chaos
Platform: UNKNOWN
Classifier: Development Status :: 4 - Beta
Classifier: Intended Audience :: Education
Classifier: Intended Audience :: Science/Research
Classifier: Operating System :: OS Independent
Classifier: License :: OSI Approved :: MIT License
Classifier: Programming Language :: Python
Classifier: Programming Language :: Python :: 3.9
Classifier: Programming Language :: Python :: Implementation :: CPython
Classifier: Topic :: Scientific/Engineering
License-File: LICENSE
Requires-Dist: numpy
Requires-Dist: pandas
Requires-Dist: scipy
Requires-Dist: sympy
Requires-Dist: matplotlib
